{
    "innerslothHats": {
        "0": "Innersloth Hats",
        "11": "Innersloth\u516c\u5f0f\u4f5c"
    },
    "nekoWasa": {
        "11": "\u732b\u91ce\u548c\u9306\u4f5c"
    },
    "nekoWasaCat": {
        "11": "\u30b3\u30c6\u30c4"
    },
    "AinuRed": {
        "11": "\u30a2\u30a4\u30cc\u30cf\u30c1\u30de\u30ad"
    },
    "AinuRedPlus": {
        "11": "\u30a2\u30a4\u30cc\u3001\u306a\u3093\u3060\u305d\u308c\u306f"
    },
    "amatohfusen": {
        "11": "\u7518\u515a\u3075\u3046\u305b\u3093"
    },
    "Gattbomb": {
        "11": "\u5927\u5909\u3084\uff01\uff01"
    },
    "censored": {
        "11": "\u898f\u5236\u6e08\u307f"
    },
    "checkers": {
        "11": "\u30c1\u30a7\u30c3\u30ab\u30fc\u30ba"
    },
    "Gatttttkoya": {
        "11": "\u30af\u30af\u30af\u305d\u3093\u306a\u3053\u3068\u306a\u3044\u3055"
    },
    "HeadOnCat": {
        "11": "\u304b\u306a\u308a\u91cd\u3044"
    },
    "MaQ": {
        "11": "\u9b54Q\u574a\u3084"
    },
    "Minidon": {
        "11": "\u9060\u8fd1\u611f\u304c\u72c2\u3046"
    },
    "nicolai": {
        "11": "\u30dc\u30eb\u59c9"
    },
    "RaimuNoah": {
        "11": "\u6765\u5922\u30ce\u30a2"
    },
    "sheep": {
        "11": "\u7f8a\u3060\uff01\uff01"
    },
    "sirusira": {
        "11": "\u30b7\u30eb\u30b7\u30e9"
    },
    "foodneko": {
        "11": "\u30d5\u30fc\u30c9\u732b"
    },
    "BlackKnight": {
        "11": "\u9ed2\u9a0e\u58eb"
    },
    "UnionJack": {
        "11": "\u706b\u85ac\u3068\u30de\u30fc\u30de\u30a4\u30c8\u306e\u9999\u308a"
    },
    "SinnekowasaZero": {
        "11": "\u65b0\u306d\u3053\u308f\u3055\u3093\u3050ZERO"
    },
    "lemonsour": {
        "11": "\u30ea\u30a2\u30eb\u3059\u304e\u305f"
    },
    "SuitJackal": {
        "11": "\u30b9\u30e0\u30fc\u30b9\u30b8\u30e3\u30c3\u30ab\u30eb"
    },
    "KindGang": {
        "11": "G\u30c1\u30ad\u304f\u30fc\u3060\u3055\u3044"
    },
    "Butasan": {
        "11": "\u30ad\u30ec\u305d\u3046"
    },
    "beamman": {
        "11": "\u30d3\u30fc\u30e0\u30de\u30f3P\u4f5c"
    },
    "bmpHat": {
        "11": "BEAMHAT"
    },
    "Pirohiko": {
        "11": "\u30d4\u30ed\u5f66\u4f5c"
    },
    "4rehe": {
        "11": "4\u30ec\u30fc\u3078T\u30b7\u30e3\u30c4"
    },
    "hinaniki": {
        "11": "\u3072\u306a\u306b\u3044\u4f5c"
    },
    "mimikkyu": {
        "11": "\u5316\u3051\u306e\u76ae"
    },
    "upa": {
        "11": "\u30a6\u30d1\u30fc"
    },
    "nitori": {
        "11": "\u306b\u3068\u308a"
    },
    "iemon": {
        "11": "\u3044\u3048\u3082\u3093"
    },
    "late": {
        "11": "\u30e9\u30c6"
    },
    "lateGuard": {
        "11": "\u5b88\u8b77\u30e9\u30c6"
    },
    "mukuro": {
        "11": "\u865a"
    },
    "mizoreHat": {
        "11": "\u307f\u305e\u308c\u5e3d"
    },
    "tacopi": {
        "11": "\u30bf\u30b3\u30d4\u30fc"
    },
    "mizore": {
        "11": "\u307f\u305e\u308c\u4f5c"
    },
    "mizoreSkin": {
        "11": "\u307f\u305e\u308c"
    },
    "mement": {
        "11": "\u3081\u3081\u3093\u3068\u3082\u308a\u4f5c"
    },
    "mementMori": {
        "11": "\u3081\u3081\u3093\u3068\u3082\u308a"
    },
    "omentMori": {
        "11": "\u304a\u3081\u3093\u3068\u3082\u308a"
    },
    "kubittake": {
        "11": "\u9996\u3063\u305f\u3051"
    },
    "Hachiman": {
        "11": "\u516b\u5e61\u5bae\u4f5c"
    },
    "gunmuss": {
        "11": "\u30ac\u30f3\u30de\u30b9"
    },
    "gunmussRocket": {
        "11": "\u30ac\u30f3\u30de\u30b9\u30ed\u30b1\u30c3\u30c8"
    },
    "hinaLuka": {
        "11": "\u30d2\u30ca\u30eb\u30ab"
    },
    "otowareLalor": {
        "11": "\u97f3\u5272\u30ec\u30a4\u30e9\u30fc"
    },
    "otowaLalor": {
        "11": "\u30ec\u30a4\u30e9\u30fc"
    },
    "gutierrez": {
        "11": "gutierrez"
    },
    "toliki": {
        "11": "\u30c6\u30a4\u30e9\u30fc"
    },
    "Miyachi": {
        "11": "\u307f\u3084\u3061\u4f5c"
    },
    "Akane": {
        "11": "\u7434\u8449\u831c"
    },
    "Akari": {
        "11": "\u7d32\u661f\u3042\u304b\u308a"
    },
    "Aoi": {
        "11": "\u7434\u8449\u8475"
    },
    "Armachan": {
        "11": "\u30a2\u30eb\u30de\u3061\u3083\u3093"
    },
    "Diachan": {
        "11": "\u30c7\u30a3\u30a2\u3061\u3083\u3093"
    },
    "flower": {
        "11": "flower"
    },
    "Hau": {
        "11": "\u96e8\u6674\u306f\u3046"
    },
    "Hime": {
        "11": "\u9cf4\u82b1\u30d2\u30e1"
    },
    "KANATA": {
        "11": "\u30ab\u30ca\u30bf"
    },
    "Kotoe": {
        "11": "\u30bf\u30f3\u30b2\u30b3\u30c8\u30a8"
    },
    "Kou": {
        "11": "\u6c34\u5948\u702c\u30b3\u30a6"
    },
    "MANA": {
        "11": "MANA"
    },
    "Metan": {
        "11": "\u56db\u56fd\u3081\u305f\u3093"
    },
    "Mikoto": {
        "11": "\u9cf4\u82b1\u30df\u30b3\u30c8"
    },
    "NAKO": {
        "11": "\u30ca\u30b3"
    },
    "Rei": {
        "11": "\u8db3\u7acb\u30ec\u30a4"
    },
    "REKO": {
        "11": "\u30ec\u30b3"
    },
    "Ritsu": {
        "11": "\u6ce2\u97f3\u30ea\u30c4"
    },
    "Rowen": {
        "11": "\u5f0f\u72fc\u7e01"
    },
    "Sora": {
        "11": "\u685c\u4e43\u305d\u3089"
    },
    "Taigen": {
        "11": "\u5f0f\u5927\u5143"
    },
    "Tsukuyomichan": {
        "11": "\u3064\u304f\u3088\u307f\u3061\u3083\u3093"
    },
    "Tsumugi": {
        "11": "\u6625\u65e5\u90e8\u3064\u3080\u304e"
    },
    "Yukari": {
        "11": "\u7d50\u6708\u3086\u304b\u308a"
    },
    "Yuzuru": {
        "11": "\u4f0a\u7e54\u5f13\u9db4"
    },
    "Zundamon": {
        "11": "\u305a\u3093\u3060\u3082\u3093"
    },
    "Ai": {
        "11": "\u6708\u8aad\u30a2\u30a4"
    },
    "Aihat": {
        "11": "\u6708\u8aad\u30a2\u30a4(\u5e3d\u5b50\u3042\u308a)"
    },
    "Allial": {
        "11": "\u30a2\u30ea\u30a2\u30eb"
    },
    "Ankomon": {
        "11": "\u3042\u3093\u3053\u3082\u3093"
    },
    "Averuni": {
        "11": "\u30a2\u30d9\u30eb\u30fc\u30cb"
    },
    "CeviMaki": {
        "11": "\u5f26\u5dfb\u30de\u30ad(Cevio)"
    },
    "IA": {
        "11": "IA"
    },
    "Itako": {
        "11": "\u6771\u5317\u30a4\u30bf\u30b3"
    },
    "Kiritan": {
        "11": "\u6771\u5317\u304d\u308a\u305f\u3093"
    },
    "Kiritanpo": {
        "11": "\u6771\u5317\u304d\u308a\u305f\u3093(\u304d\u308a\u305f\u3093\u307d)"
    },
    "Maki": {
        "11": "\u5f26\u5dfb\u30de\u30ad"
    },
    "Millial": {
        "11": "\u30df\u30ea\u30a2\u30eb"
    },
    "ONE": {
        "11": "ONE"
    },
    "Sasara": {
        "11": "\u3055\u3068\u3046\u3055\u3055\u3089"
    },
    "Seika": {
        "11": "\u4eac\u753a\u30bb\u30a4\u30ab"
    },
    "Syouta": {
        "11": "\u6708\u8aad\u30b7\u30e7\u30a6\u30bf"
    },
    "Takahashi": {
        "11": "\u30bf\u30ab\u30cf\u30b7"
    },
    "Tsudumi": {
        "11": "\u3059\u305a\u304d\u3064\u3065\u307f"
    },
    "Tuina": {
        "11": "\u3064\u3044\u306a\u3061\u3083\u3093"
    },
    "TuinaMen": {
        "11": "\u3064\u3044\u306a\u3061\u3083\u3093(\u30c7\u30a3\u30af\u30bd\u30f3)"
    },
    "Una": {
        "11": "\u97f3\u8857\u30a6\u30ca"
    },
    "Unahat": {
        "11": "\u97f3\u8857\u30a6\u30ca(\u30aa\u30bf\u30de\u30f3\u5e3d)"
    },
    "Unoka": {
        "11": "\u7fbd\u30ce\u83ef"
    },
    "Zunko": {
        "11": "\u6771\u5317\u305a\u3093\u5b50"
    },
    "AkaneSy": {
        "11": "\u7434\u8449\u831c(Synthesizer V)"
    },
    "AkariAI": {
        "11": "\u7d32\u661f\u3042\u304b\u308a AI"
    },
    "AkariTu": {
        "11": "\u7d32\u661f\u3042\u304b\u308a \u857e"
    },
    "AoiSy": {
        "11": "\u7434\u8449\u8475(Synthesizer V)"
    },
    "Chifuyu": {
        "11": "\u82b1\u9688\u5343\u51ac"
    },
    "Karin": {
        "11": "\u590f\u8272\u82b1\u68a8"
    },
    "Kiritan2": {
        "11": "\u6771\u5317\u304d\u308a\u305f\u3093 \u79c1\u670d"
    },
    "Kiritanpo2": {
        "11": "\u6771\u5317\u304d\u308a\u305f\u3093 \u79c1\u670d(\u304d\u308a\u305f\u3093\u307d)"
    },
    "Kou2": {
        "11": "\u6c34\u5948\u702c\u30b3\u30a6(\u4e0a\u7740\u3042\u308a)"
    },
    "Ohoshi": {
        "11": "\u304a\u661f"
    },
    "Rikka": {
        "11": "\u5c0f\u6625\u516d\u82b1"
    },
    "SasaraAI": {
        "11": "\u3055\u3068\u3046\u3055\u3055\u3089 AI"
    },
    "Tobari": {
        "11": "\u591c\u8a9e\u30c8\u30d0\u30ea"
    },
    "TsudumiAI": {
        "11": "\u3059\u305a\u304d\u3064\u3065\u307f AI"
    },
    "YukariAI": {
        "11": "\u7d50\u6708\u3086\u304b\u308a AI"
    },
    "Yukarisizuku": {
        "11": "\u7d50\u6708\u3086\u304b\u308a \u96eb"
    },
    "AkaneGo": {
        "11": "\u7434\u8449\u831c\uff08\u30b4\u30b7\u30c3\u30af\uff09"
    },
    "AkaneSe": {
        "11": "\u7434\u8449\u831c\uff08Seiren Voice\uff09"
    },
    "Akari2": {
        "11": "\u7d32\u661f\u3042\u304b\u308a\uff08\u30b8\u30e3\u30b1\u30c3\u30c8\u7121\u3057\uff09"
    },
    "Ankomon2": {
        "11": "\u3042\u3093\u3053\u3082\u3093\uff08\u5996\u7cbe\uff09"
    },
    "AoiGo": {
        "11": "\u7434\u8449\u8475\uff08\u30b4\u30b7\u30c3\u30af\uff09"
    },
    "AoiSe": {
        "11": "\u7434\u8449\u8475\uff08Seiren Voice\uff09"
    },
    "Mochiko": {
        "11": "\u3082\u3061\u5b50"
    },
    "YukariO": {
        "11": "\u7d50\u6708\u3086\u304b\u308a\u306e\u53cc\u5b50\u306e\u5f1f"
    },
    "Yuzuru2": {
        "11": "\u4f0a\u7e54\u5f13\u9db4\uff08\u30b7\u30e3\u30c4\u3042\u308a\uff09"
    },
    "YuzuruSe": {
        "11": "\u4f0a\u7e54\u5f13\u9db4\uff08Seiren Voice\uff09"
    },
    "Zundamon2": {
        "11": "\u305a\u3093\u3060\u3082\u3093\uff08\u5996\u7cbe\uff09"
    },
    "ZunkoZ": {
        "11": "\u6771\u5317\u305a\u3093\u3053\uff08\u305a\u3093\u3060\u3082\u3093\uff09"
    },
    "ZZKashiwa": {
        "11": "\u304b\u3057\u308f\u3082\u3061"
    },
    "ZZOhagia": {
        "11": "\u304a\u306f\u304e\uff08\u3042\u3093\u3053\uff09"
    },
    "ZZOhagik": {
        "11": "\u304a\u306f\u304e\uff08\u304d\u306a\u3053\uff09"
    },
    "ZZZunda": {
        "11": "\u305a\u3093\u3060\u3082\u3061"
    },
    "YJSiroSakura": {
        "11": "YJ*\u767d\u685c\u4f5c"
    },
    "AK": {
        "11": "\u3061\u3087\u3063\u3068\u6b66\u5668\u5eab\u3067\u501f\u308a\u3066\u304d\u305f"
    },
    "ahoge": {
        "11": "\u53cc\u8449\u30a2\u30db\u6bdb"
    },
    "doubleKiller": {
        "11": "\u30c0\u30d6\u30eb\u30ad\u30e9\u30fc"
    },
    "echo": {
        "11": "ECHO"
    },
    "sandWich": {
        "11": "\u30b5\u30f3\u30c9\u30a4\u30c3\u30c1"
    },
    "live": {
        "11": "\u914d\u4fe1\u4e2d"
    },
    "ninshoBadge": {
        "11": "\u8a8d\u8a3c\u30d0\u30c3\u30b8"
    },
    "redPlay": {
        "11": "\u3069\u3093\u306a\u72b6\u6cc1\u3067\u3082\u30d7\u30ec\u30a4"
    },
    "saimin": {
        "11": "\u81ea\u5206\u3078\u50ac\u7720\u8853"
    },
    "sairiumu": {
        "11": "\u30b5\u30a4\u30ea\u30a6\u30e0"
    },
    "starRod": {
        "11": "\u30b9\u30bf\u30fc\u30ed\u30c3\u30c9"
    },
    "mop": {
        "11": "\u30e2\u30c3\u30d7\u639b\u3051\u3092\u5fd8\u308c\u305a\u306b"
    },
    "o2": {
        "11": "\u9178\u7d20\u3092\u3068\u3063\u3066\u304a\u3053\u3046"
    },
    "hydration": {
        "11": "\u89b3\u5149\u306b\u306f\u6c34\u5206\u88dc\u7d66"
    },
    "yojo": {
        "11": "\u3087\u3045\u3058\u3087"
    },
    "eyemask": {
        "11": "\u79c1\u306f\u5bdd\u3066\u3044\u307e\u305b\u3093"
    },
    "usbHacker": {
        "11": "USB\u30cf\u30c3\u30ab\u30fc"
    },
    "4gou": {
        "11": "4\u53f7"
    },
    "utyuJin": {
        "11": "\u5b87\u5b99\u4eba\u3060\u3088"
    },
    "nobaman": {
        "11": "\u8edf\u7981\u30b3\u30fc\u30b9\u30bf\u30fc\u7ba1\u7406\u8005"
    },
    "onigiri": {
        "11": "\u304a\u306b\u304e\u308a"
    },
    "tellmebeat": {
        "11": "\u30c6\u30eb\u30df\u30fc\u30d3\u30fc\u30c9"
    },
    "myon": {
        "11": "\u307f\u3087\u307f\u3087\u307f\u3087\u307f\u3087\uff5e\u3093"
    },
    "satori": {
        "11": "\u5c0f5+\u30ed\u30ea=\u609f\u308a"
    },
    "standImpostor": {
        "11": "\u30b9\u30bf\u30f3\u30c9:\u30a4\u30f3\u30dd\u30b9\u30bf\u30fc"
    },
    "crewJuice": {
        "11": "\u30af\u30eb\u30fc\u30b8\u30e5\u30fc\u30b9"
    },
    "gomibako": {
        "11": "\u524a\u96643\u79d2\u524d"
    },
    "silverShield": {
        "11": "\u9280\u306e\u76fe"
    },
    "uboa": {
        "11": "\u30a6\u30dc\u30a1"
    },
    "dokkingNiboshi": {
        "11": "\u30c9\u30c3\u30ad\u30f3\u30b0\u306b\u307c\u3057"
    },
    "pickaxeHead": {
        "11": "\u982d\u75db"
    },
    "thinking": {
        "11": "\u60a9\u307f"
    },
    "yj": {
        "11": "YJ*"
    },
    "jevil": {
        "11": "\u30b8\u30a7\u30d3\u30eb"
    },
    "madadesuka": {
        "11": "\u307e\u3060\u3067\u3059\u304b\uff1f"
    },
    "breadeat": {
        "11": "\u30d1\u30f3\u306f\u304a\u3044\u3057\u3044"
    },
    "handmike": {
        "11": "\u6b4c\u3048"
    },
    "hatmuff": {
        "11": "\u30cf\u30c3\u30c8&\u30de\u30d5\u30e9\u30fc"
    },
    "jokercard": {
        "11": "Joker"
    },
    "parasite": {
        "11": "\u5bc4\u751f\u4e2d"
    },
    "pcngus": {
        "11": "\u30ab\u30f3\u30cb\u30f3\u30b0"
    },
    "sus": {
        "11": "SUS"
    },
    "suschiken": {
        "11": "\u30c1\u30ad\u30f31\u3064"
    },
    "SakuraWhite": {
        "11": "\u767d\u685c"
    },
    "SakuraBlack": {
        "11": "\u9ed2\u685c"
    },
    "SakuraWhiteBlack": {
        "11": "\u767d\u9ed2\u685c"
    },
    "Arrow": {
        "11": "\u77e2\u5370"
    },
    "OldGlass": {
        "11": "\u56db\u89d2\u3044\u9854"
    },
    "Mystery": {
        "11": "\u8b0e\u306e\u5b58\u5728"
    },
    "YJ_Eraser": {
        "11": "\u81ea\u5206\u304c\u6d88\u3057\u30b4\u30e0"
    },
    "SelfControl": {
        "11": "\u5236\u5fa1\u306f\u81ea\u5206\u3067"
    },
    "thumbtack": {
        "11": "\u753b\u92f2"
    },
    "SuperBurger": {
        "11": "\u3067\u304b\u3059\u304e\u308b\u30d0\u30fc\u30ac\u30fc"
    },
    "SuperPotato": {
        "11": "\u591a\u3059\u304e\u308b\u30d5\u30e9\u30a4\u30c9\u30dd\u30c6\u30c8"
    },
    "SuperCola": {
        "11": "\u3044\u3063\u3071\u3044\u98f2\u3081\u308b\u30b3\u30fc\u30e9"
    },
    "itow": {
        "11": "\u3044\u3068\u3046\u4f5c"
    },
    "tomokaEB": {
        "11": "\u30c8\u30e2\u30abEB"
    },
    "yamatoBeetle": {
        "11": "\u30ab\u30d6\u30c8\u30e0\u30b7"
    },
    "yamatoBeetleBrown": {
        "11": "\u30ab\u30d6\u30c8\u30e0\u30b7_\u8336"
    },
    "Kurodoru": {
        "11": "\u30af\u30ed\u30c9\u30eb\u4f5c"
    },
    "zombie": {
        "11": "\u30be\u30f3\u30d3"
    },
    "GoodToBeAlive": {
        "11": "Good To Be Alive"
    },
    "unhappyset": {
        "11": "\u30a2\u30f3\u30cf\u30c3\u30d4\u30fc\u30bb\u30c3\u30c8\u4f5c"
    },
    "taskbar": {
        "0": "taskbar",
        "11": "\u30bf\u30b9\u30af\u30d0\u30fc"
    },
    "babble": {
        "0": "capsule",
        "11": "\u30ab\u30d7\u30bb\u30eb"
    },
    "mochimochicrewmate": {
        "11": "\u3082\u3061\u3082\u3061\u30af\u30eb\u30fc"
    },
    "misosiru": {
        "0": "misosoup",
        "11": "\u5473\u564c\u6c41"
    },
    "fire": {
        "11": "\u706b\u4e8b"
    },
    "bigcolorcone": {
        "11": "\u5de8\u5927\u30ab\u30e9\u30fc\u30b3\u30fc\u30f3"
    },
    "genocide": {
        "11": "\u30b8\u30a7\u30ce\u30b5\u30a4\u30c9"
    },
    "ice": {
        "11": "\u30a2\u30a4\u30b9"
    },
    "rapu": {
        "11": "\u3089\u3077\u4f5c"
    },
    "ParasiticWormwood": {
        "11": "\u5bc4\u751f\u866b"
    },
    "ImpostorFinalform": {
        "11": "\u30a4\u30f3\u30dd\u30b9\u30bf\u30fc\u6700\u7d42\u5f62\u614b(FNF)"
    },
    "basicimpostor": {
        "0": "BasicImpostor",
        "11": "\u30d9\u30fc\u30b7\u30c3\u30af\u30a4\u30f3\u30dd\u30b9\u30bf\u30fc"
    },
    "HolyBeast": {
        "11": "\u8056\u306a\u308b\u7363"
    },
    "Spinosaurus": {
        "11": "\u30b9\u30d4\u30ce\u30b5\u30a6\u30eb\u30b9"
    },
    "Humanoid": {
        "0": "Humanoid",
        "11": "\u4eba\u578b"
    },
    "noraushi": {
        "11": "\u91ce\u826f\u725b\u4f5c"
    },
    "noraushiHat": {
        "11": "\u91ce\u826f\u725b"
    },
    "romuniki": {
        "11": "ROMniki"
    },
    "yuri": {
        "11": "\u3086\u30fc\u308a"
    },
    "iva": {
        "11": "iVa"
    },
    "oyakimon": {
        "11": "\u304a\u3084\u304d\u3082\u3093\u4f5c"
    },
    "oyaki": {
        "11": "\u3067\u304b\u3044\u304a\u3084\u304d"
    },
    "turunoda": {
        "11": "\u3060\u3058\u3083\u308c\u3082\u3093\u306f\u540a\u308b\u306e\u3060\u3002"
    },
    "onore_Impostor": {
        "11": "\u304a\u306e\u308c\u30a4\u30f3\u30dd\u30b9\u30bf\u30fc\uff01"
    },
    "onore_Jackal": {
        "11": "\u304a\u306e\u308c\u30b8\u30e3\u30c3\u30ab\u30eb\uff01"
    },
    "tinfoil_hat": {
        "11": "\u601d\u8003\u76d7\u8074\u5bfe\u7b56"
    },
    "oyaki_mini": {
        "11": "\u30df\u30cb\u304a\u3084\u304d"
    },
    "karappomon": {
        "11": "\u304b\u3089\u3063\u307d\u3082\u3093\u4f5c"
    },
    "bom_maimai": {
        "11": "\u30d0\u30af\u30c0\u30f3\u30de\u30a4\u30de\u30a4"
    },
    "beer_maimai": {
        "11": "\u30d3\u30fc\u30eb\u30de\u30a4\u30de\u30a4"
    },
    "arumikan_turunoda": {
        "11": "\u3042\u308b\u30df\u30ab\u30f3\uff08\u3064\u308b\u306e\u3060\uff09"
    },
    "arumikan_zundamon": {
        "11": "\u3042\u308b\u30df\u30ab\u30f3\uff08ZUNDAMON\uff09"
    },
    "arumikan_zundanrg": {
        "11": "\u3042\u308b\u30df\u30ab\u30f3\uff08ZUNDANRG\uff09"
    },
    "arumikan_grape": {
        "11": "\u3042\u308b\u30df\u30ab\u30f3\uff08\u30b0\u30ec\u30fc\u30d7\uff09"
    },
    "arumikan_tea": {
        "11": "\u3042\u308b\u30df\u30ab\u30f3\uff08\u304a\u8336\uff09"
    },
    "arumikan_zunpis": {
        "11": "\u3042\u308b\u30df\u30ab\u30f3\uff08\u30ba\u30f3\u30d4\u30b9\uff09"
    },
    "oyaki_maimai": {
        "11": "\u30aa\u30e4\u30ad\u30de\u30a4\u30de\u30a4"
    },
    "short_maimai": {
        "11": "\u3051\u30fc\u304d\u307e\u3044\u307e\u3044"
    },
    "maimai_oyaki_reinoshippo": {
        "11": "\u3057\u3063\u307d\u5165\u308a\u304a\u3084\u304d\u30de\u30a4\u30de\u30a4"
    },
    "maimai_oyaki_zunshippo": {
        "11": "\u305a\u3093\u3057\u3063\u307d\u304a\u3084\u304d\u30de\u30a4\u30de\u30a4"
    },
    "maimai_purin": {
        "11": "\u30d7\u30ea\u30f3\u30de\u30a4\u30de\u30a4"
    },
    "mint_maimai": {
        "11": "\u30c1\u30e7\u30b3\u30df\u30f3\u30c8\u30de\u30a4\u30de\u30a4"
    },
    "moon_big": {
        "11": "\u6708\u304c\u7dba\u9e97\u3067\u3059\u306d"
    },
    "moon_mini": {
        "11": "\u6708\u306f\u51fa\u3066\u3044\u308b\u304b\uff1f"
    },
    "Takeman": {
        "11": "\u7af9\u9945\u4f5c"
    },
    "T_IronPick": {
        "11": "IronPick"
    },
    "T_Defeat": {
        "11": "Defeat"
    },
    "T_Pickaxe": {
        "11": "\u30c0\u30a4\u30e4\u30d4\u30c3\u30b1\u30eb"
    },
    "Nyayuta": {
        "11": "Nyayuta\u4f5c"
    },
    "trickAndTreat": {
        "11": "\u30c8\u30ea\u30c3\u30af\uff06\u30c8\u30ea\u30fc\u30c8"
    },
    "meronpan": {
        "11": "\u30e1\u30ed\u30f3\u30d1\u30f3"
    },
    "gunman": {
        "11": "\u30ac\u30f3\u30de\u30f3"
    },
    "Yu": {
        "11": "Yu\u4f5c"
    },
    "AibayashiMizuki": {
        "11": "\u85cd\u6797\u745e\u5e0c"
    },
    "AzaminoHinata": {
        "11": "\u8387\u91ce\u30d2\u30ca\u30bf"
    },
    "CITYHATANUKI": {
        "11": "\u30b7\u30c6\u30a3\u6d3e\u305f\u306c\u304d"
    },
    "KatagiriKonsuke": {
        "11": "\u7247\u6850\u7d3a\u4ecb"
    },
    "KawarabeKumaji": {
        "11": "\u5ddd\u539f\u8fba\u718a\u5c13"
    },
    "mutari": {
        "11": "\u3080\u305f\u30ea"
    },
    "NekoNoKnmichi": {
        "11": "\u732b\u306e\u5c0f\u9053"
    },
    "nekomatamasao": {
        "11": "\u732b\u53c9\u307e\u3055\u304a"
    },
    "ShimizuAlm": {
        "11": "\u679d\u6c34\u30a2\u30eb\u30e0"
    },
    "YuHat": {
        "11": "Yu"
    },
    "YukitoFuyumori": {
        "11": "\u51ac\u68ee\u3086\u304d\u3068"
    },
    "YukizukiNoir": {
        "11": "\u96ea\u6708\u30ce\u30a2"
    },
    "UzomuZo": {
        "11": "\u30a6\u30be\u30fc\u30e0\u8c61\u4f5c"
    },
    "EyeLight_Blue": {
        "11": "\u30a2\u30a4\u30e9\u30a4\u30c8(\u9752)"
    },
    "EyeLight_Green": {
        "11": "\u30a2\u30a4\u30e9\u30a4\u30c8(\u7dd1)"
    },
    "EyeLight_Red": {
        "11": "\u30a2\u30a4\u30e9\u30a4\u30c8(\u8d64)"
    },
    "EyeLight_Yellow": {
        "11": "\u30a2\u30a4\u30e9\u30a4\u30c8(\u9ec4)"
    },
    "Mono_EyeLight_Blue": {
        "11": "\u30a2\u30a4\u30e9\u30a4\u30c8(\u9752\u30fb\u5358)"
    },
    "Mono_EyeLight_Green": {
        "11": "\u30a2\u30a4\u30e9\u30a4\u30c8(\u7dd1\u30fb\u5358)"
    },
    "Mono_EyeLight_Red": {
        "11": "\u30a2\u30a4\u30e9\u30a4\u30c8(\u8d64\u30fb\u5358)"
    },
    "Mono_EyeLight_Yellow": {
        "11": "\u30a2\u30a4\u30e9\u30a4\u30c8(\u9ec4\u30fb\u5358)"
    },
    "Halo": {
        "11": "\u5f8c\u5149"
    },
    "JackOHead": {
        "11": "\u30ab\u30dc\u30c1\u30e3\u982d"
    },
    "Long-tailed_Tit": {
        "11": "\u30b7\u30de\u30a8\u30ca\u30ac"
    },
    "Sparrow": {
        "11": "\u30b9\u30ba\u30e1"
    },
    "Snowman": {
        "11": "\u96ea\u3060\u308b\u307e"
    },
    "SnowmanColor": {
        "11": "\u96ea\u3060\u308b\u307e(\u30ab\u30e9\u30fc\u5bfe\u5fdc)"
    },
    "Booster": {
        "11": "\u30d6\u30fc\u30b9\u30bf\u30fc"
    },
    "Faceless": {
        "11": "\u306e\u3063\u307a\u3089\u307c\u3046"
    },
    "Hands_of_the_Dead": {
        "11": "\u4ea1\u8005\u306e\u624b"
    },
    "I_am_Werewolf": {
        "11": "\u6211\u306f\u4eba\u72fc\u306a\u308a"
    },
    "WorkHelmet_Yellow": {
        "11": "\u30d8\u30eb\u30e1\u30c3\u30c8(\u9ec4)"
    },
    "kannagi_drive": {
        "11": "\u304b\u3093\u306a\u304e\u30c9\u30e9\u30a4\u30d6\u4f5c"
    },
    "owamura": {
        "11": "\u7d42\u308f\u308a\u3084\u3053\u3093\u306a\u6751\u30a1!"
    },
    "kannagi": {
        "0": "kannagi",
        "11": "\u304b\u3093\u306a\u304e\u30c9\u30e9\u30a4\u30d6"
    },
    "aiueojyun": {
        "0": "aiueojyun",
        "11": "\u3042\u3044\u3046\u3048\u304a\u9806\u3067\u540a\u308d\u3046\u305c"
    },
    "anmaridesuwa": {
        "0": "anmaridesuwa",
        "11": "\u3042\u3093\u307e\u308a\u3067\u3059\u308f\u30fc"
    },
    "bobebagyua": {
        "0": "bobebagyua",
        "11": "\u307c\u3079\u3070\u304e\u3085\u3042"
    },
    "crew_dokoya": {
        "0": "crew_dokoya",
        "11": "\u30af\u30eb\u30fc\u3069\u3053\u3084\u30fc"
    },
    "Impostor_dokoya": {
        "0": "Impostor_dokoya",
        "11": "\u30a4\u30f3\u30dd\u30b9\u30bf\u30fc\u3069\u3053\u3084\u30fc"
    },
    "hai_gattyan": {
        "0": "hai_gattyan",
        "11": "\u306f\u3044\u304c\u3063\u3061\u3083\u30fc\u3093"
    },
    "jitouhyou": {
        "0": "jitouhyou",
        "11": "\u79c1\u306f\u79c1\u306b\u6295\u7968\u3057\u307e\u3059"
    },
    "kenzenketu": {
        "0": "kenzenketu",
        "11": "\u5065\u5168\u30e4\u30c3\u30bf\u30fc"
    },
    "tukihatu": {
        "11": "\u725b\u4e73\u5148\u751f\u4f5c"
    },
    "milk_big": {
        "11": "\u7b49\u8eab\u5927\u725b\u4e73\u30d1\u30c3\u30af"
    },
    "milk_rainbow": {
        "11": "\u30ec\u30a4\u30f3\u30dc\u30fc\u30d1\u30c3\u30af"
    },
    "milk_coffee": {
        "11": "\u30b3\u30fc\u30d2\u30fc\u30df\u30eb\u30af"
    },
    "Composter": {
        "11": "\u30b3\u30f3\u30dd\u30b9\u30bf\u30fc\u4f5c"
    },
    "among guys": {
        "11": "\u30a2\u30e2\u30f3\u30b0 \u30ac\u30a4\u30ba"
    },
    "beast": {
        "11": "\u7363"
    },
    "beast_of_prey": {
        "11": "\u731b\u7363"
    },
    "Miso_soup": {
        "11": "\u5473\u564c\u6c41"
    },
    "witch": {
        "11": "\u9b54\u5973"
    }
}